[
  {
    "hex": "a3db1c",
    "name": "Airborne Tactical Advantage",
    "category": "Hired Gun",
    "callsign": "N348AX",
    "lon": -87.8207,
    "lat": 29.2614,
    "alt": 9738.36,
    "velocity": 254.74,
    "heading": 242.19,
    "trace": [
      [
        29.8956,
        -88.1433
      ],
      [
        29.2614,
        -87.8207
      ]
    ]
  },
  {
    "hex": "a7496d",
    "name": "Meta Aerospace",
    "category": "Hired Gun",
    "callsign": "SWB90",
    "lon": -117.2494,
    "lat": 33.8665,
    "alt": 426.72,
    "velocity": 78.17,
    "heading": 329.55,
    "trace": [
      [
        31.8162,
        -80.0406
      ],
      [
        31.2802,
        -81.0396
      ],
      [
        32.2837,
        -87.2088
      ],
      [
        32.0142,
        -95.5875
      ],
      [
        31.7545,
        -101.0493
      ],
      [
        31.9038,
        -104.3472
      ],
      [
        32.7229,
        -110.109
      ],
      [
        33.5578,
        -113.5261
      ],
      [
        33.8665,
        -117.2494
      ]
    ]
  },
  {
    "hex": "a0f8f9",
    "name": "Atlas Air",
    "category": "Hired Gun",
    "callsign": "GTI5768",
    "lon": -92.5987,
    "lat": 35.038,
    "alt": 10972.8,
    "velocity": 253.94,
    "heading": 232.57,
    "trace": [
      [
        37.5431,
        -87.8609
      ],
      [
        35.038,
        -92.5987
      ]
    ]
  },
  {
    "hex": "a2c4e0",
    "name": "Global Crossing Airlines",
    "category": "Hired Gun",
    "callsign": "GXA6142",
    "lon": -83.6265,
    "lat": 35.6935,
    "alt": 10972.8,
    "velocity": 227.58,
    "heading": 236.06,
    "trace": [
      [
        39.6129,
        -76.7524
      ],
      [
        37.9598,
        -79.1717
      ],
      [
        35.6935,
        -83.6265
      ]
    ]
  },
  {
    "hex": "a3e4e3",
    "name": "Airborne Tactical Advantage",
    "category": "Hired Gun",
    "callsign": "N350AX",
    "lon": -87.8224,
    "lat": 29.6685,
    "alt": 9563.1,
    "velocity": 242.31,
    "heading": 270.24,
    "trace": [
      [
        29.8562,
        -88.0922
      ],
      [
        29.6685,
        -87.8224
      ]
    ]
  },
  {
    "hex": "a4c6b8",
    "name": "Airborne Tactical Advantage",
    "category": "Hired Gun",
    "callsign": "N407AX",
    "lon": -87.7788,
    "lat": 29.131,
    "alt": 6271.26,
    "velocity": 259.13,
    "heading": 152.06,
    "trace": [
      [
        29.9319,
        -88.119
      ],
      [
        29.131,
        -87.7788
      ]
    ]
  },
  {
    "hex": "a5ad74",
    "name": "Phoenix Air",
    "category": "Hired Gun",
    "callsign": "N465PA",
    "lon": -118.844,
    "lat": 34.399,
    "alt": 2011.68,
    "velocity": 127.8,
    "heading": 215.99,
    "trace": [
      [
        34.399,
        -118.844
      ]
    ]
  },
  {
    "hex": "a7a2be",
    "name": "ISR Platforms",
    "category": "Hired Gun",
    "callsign": "",
    "lon": 125.012,
    "lat": 37.1947,
    "alt": 11582.4,
    "velocity": 157.3,
    "heading": 262.29,
    "trace": [
      [
        37.1947,
        125.012
      ]
    ]
  },
  {
    "hex": "a4b7dc",
    "name": "Airborne Tactical Advantage",
    "category": "Hired Gun",
    "callsign": "N403AX",
    "lon": -87.2685,
    "lat": 29.7408,
    "alt": 7246.62,
    "velocity": 256.39,
    "heading": 100.52,
    "trace": [
      [
        29.9415,
        -88.1525
      ],
      [
        29.7408,
        -87.2685
      ]
    ]
  },
  {
    "hex": "a81dc1",
    "name": "Airborne Tactical Advantage",
    "category": "Hired Gun",
    "callsign": "STK42",
    "lon": -98.3972,
    "lat": 32.6615,
    "alt": 2179.32,
    "velocity": 204.69,
    "heading": 58.99,
    "trace": [
      [
        32.864,
        -98.2414
      ],
      [
        32.7159,
        -98.6481
      ],
      [
        32.6615,
        -98.3972
      ]
    ]
  },
  {
    "hex": "a86e85",
    "name": "Global Crossing Airlines",
    "category": "Hired Gun",
    "callsign": "GXA6153",
    "lon": -103.8631,
    "lat": 31.912,
    "alt": 10363.2,
    "velocity": 224.38,
    "heading": 279.64,
    "trace": [
      [
        31.3278,
        -95.9316
      ],
      [
        31.4363,
        -98.9327
      ],
      [
        31.912,
        -103.8631
      ]
    ]
  },
  {
    "hex": "a384b0",
    "name": "Airborne Tactical Advantage",
    "category": "Hired Gun",
    "callsign": "N326AX",
    "lon": -117.0776,
    "lat": 31.2114,
    "alt": 3916.68,
    "velocity": 170.98,
    "heading": 161.95,
    "trace": [
      [
        33.2711,
        -119.0058
      ],
      [
        32.0352,
        -117.4816
      ],
      [
        31.2114,
        -117.0776
      ]
    ]
  },
  {
    "hex": "a0fd43",
    "name": "Draken Intl",
    "category": "Hired Gun",
    "callsign": "SCOOTAA2",
    "lon": -77.1655,
    "lat": 34.7365,
    "alt": 6865.62,
    "velocity": 237.84,
    "heading": 42.11,
    "trace": [
      [
        34.8953,
        -76.8839
      ],
      [
        34.9582,
        -76.9187
      ],
      [
        34.7365,
        -77.1655
      ]
    ]
  },
  {
    "hex": "ab7437",
    "name": "Global Crossing Airlines",
    "category": "Hired Gun",
    "callsign": "GXA6110",
    "lon": -90.5256,
    "lat": 14.5857,
    "alt": null,
    "velocity": 0.51,
    "heading": 340.31,
    "trace": [
      [
        14.4466,
        -90.2121
      ],
      [
        14.5855,
        -90.5256
      ],
      [
        14.5857,
        -90.5256
      ]
    ]
  },
  {
    "hex": "157716",
    "name": "Russia Special Flight Detachment",
    "category": "Dictator Alert",
    "callsign": "RSD510",
    "lon": -38.2535,
    "lat": -3.581,
    "alt": 10652.76,
    "velocity": 245.15,
    "heading": 57.08,
    "trace": [
      [
        -3.581,
        -38.2535
      ]
    ]
  }
]