[
  {
    "hex": "896264",
    "name": "Abu Dhabi Amiri Flight",
    "category": "Dictator Alert",
    "callsign": "AUH03",
    "lon": -73.1053,
    "lat": -4.345,
    "alt": 13106.4,
    "velocity": 245.43,
    "heading": 338.87,
    "trace": [
      [
        -4.345,
        -73.1053
      ]
    ]
  },
  {
    "hex": "a835d1",
    "name": "Global Crossing Airlines",
    "category": "Hired Gun",
    "callsign": "GXA201",
    "lon": -72.3932,
    "lat": 18.7305,
    "alt": 10965.18,
    "velocity": 226.55,
    "heading": 331.22,
    "trace": [
      [
        18.7305,
        -72.3932
      ]
    ]
  },
  {
    "hex": "896572",
    "name": "Abu Dhabi Amiri Flight",
    "category": "Dictator Alert",
    "callsign": "AUH07",
    "lon": -127.4074,
    "lat": 44.4543,
    "alt": 11574.78,
    "velocity": 237.67,
    "heading": 180,
    "trace": [
      [
        47.4333,
        -119.6055
      ],
      [
        48.0607,
        -120.664
      ],
      [
        47.9888,
        -122.1103
      ],
      [
        47.4811,
        -123.4124
      ],
      [
        46.8563,
        -124.3185
      ],
      [
        44.4543,
        -127.4074
      ]
    ]
  },
  {
    "hex": "406e9f",
    "name": "AirTanker",
    "category": "Hired Gun",
    "callsign": "UBT783",
    "lon": -80.5696,
    "lat": 32.186,
    "alt": 12192,
    "velocity": 211.64,
    "heading": 212.49,
    "trace": [
      [
        47.5596,
        -61.8285
      ],
      [
        46.2295,
        -64.9643
      ],
      [
        44.915,
        -67.6383
      ],
      [
        43.2574,
        -69.8324
      ],
      [
        41.1665,
        -72.2134
      ],
      [
        40.1196,
        -73.3046
      ],
      [
        38.617,
        -74.8848
      ],
      [
        36.8505,
        -76.5848
      ],
      [
        35.6315,
        -77.7249
      ],
      [
        34.9885,
        -78.3337
      ],
      [
        32.186,
        -80.5696
      ]
    ]
  },
  {
    "hex": "a75013",
    "name": "Global Crossing Airlines",
    "category": "Hired Gun",
    "callsign": "GXA6141",
    "lon": -74.9233,
    "lat": 40.8251,
    "alt": 2087.88,
    "velocity": 153.47,
    "heading": 113.3,
    "trace": [
      [
        27.6427,
        -96.9113
      ],
      [
        30.1243,
        -95.3826
      ],
      [
        31.9254,
        -93.9693
      ],
      [
        34.1385,
        -91.3859
      ],
      [
        36.284,
        -88.827
      ],
      [
        37.4457,
        -87.6882
      ],
      [
        38.9693,
        -85.6522
      ],
      [
        40.6593,
        -82.8809
      ],
      [
        41.7177,
        -80.7368
      ],
      [
        41.6812,
        -79.4256
      ],
      [
        40.8251,
        -74.9233
      ]
    ]
  },
  {
    "hex": "8953e3",
    "name": "Gov of Brunei",
    "category": "Dictator Alert",
    "callsign": "V8OAS",
    "lon": 103.1931,
    "lat": 12.385,
    "alt": 10972.8,
    "velocity": 265.14,
    "heading": 301.59,
    "trace": [
      [
        10.5116,
        106.967
      ],
      [
        12.385,
        103.1931
      ]
    ]
  },
  {
    "hex": "ab7437",
    "name": "Global Crossing Airlines",
    "category": "Hired Gun",
    "callsign": "GXA6216",
    "lon": -109.8774,
    "lat": 28.8972,
    "alt": 9464.04,
    "velocity": 243.31,
    "heading": 118.41,
    "trace": [
      [
        28.8972,
        -109.8774
      ]
    ]
  },
  {
    "hex": "a6b0f5",
    "name": "Global Crossing Airlines",
    "category": "Hired Gun",
    "callsign": "GXA6182",
    "lon": -95.0332,
    "lat": 29.6649,
    "alt": 10363.2,
    "velocity": 225.52,
    "heading": 231.48,
    "trace": [
      [
        29.6649,
        -95.0332
      ]
    ]
  },
  {
    "hex": "157713",
    "name": "Russia Special Flight Detachment",
    "category": "Dictator Alert",
    "callsign": "RSD958",
    "lon": 37.4303,
    "lat": 55.9765,
    "alt": 632.46,
    "velocity": 27.63,
    "heading": 155.82,
    "trace": [
      [
        55.6081,
        39.7057
      ],
      [
        55.9765,
        37.4303
      ]
    ]
  }
]