[
  {
    "hex": "ad3c48",
    "name": "National Airlines",
    "category": "Hired Gun",
    "callsign": "NCR852",
    "lon": -95.3807,
    "lat": 34.3309,
    "alt": 9570.72,
    "velocity": 238.18,
    "heading": 219.74,
    "trace": [
      [
        41.99,
        -87.9123
      ],
      [
        40.6469,
        -88.664
      ],
      [
        39.5133,
        -89.8325
      ],
      [
        38.7848,
        -90.5939
      ],
      [
        38.1806,
        -91.3671
      ],
      [
        36.6953,
        -92.9475
      ],
      [
        34.3309,
        -95.3807
      ]
    ]
  },
  {
    "hex": "a2d25e",
    "name": "Global Crossing Airlines",
    "category": "Hired Gun",
    "callsign": "GXA6231",
    "lon": -97.4869,
    "lat": 26.7453,
    "alt": 3116.58,
    "velocity": 160.27,
    "heading": 212.41,
    "trace": [
      [
        30.8571,
        -93.2962
      ],
      [
        30.2925,
        -93.9299
      ],
      [
        28.9219,
        -95.4252
      ],
      [
        26.7453,
        -97.4869
      ]
    ]
  },
  {
    "hex": "a2c4e0",
    "name": "Global Crossing Airlines",
    "category": "Hired Gun",
    "callsign": "GXA6142",
    "lon": -89.0747,
    "lat": 32.9599,
    "alt": 11582.4,
    "velocity": 230.54,
    "heading": 230.34,
    "trace": [
      [
        40.7023,
        -74.1672
      ],
      [
        40.5909,
        -74.9008
      ],
      [
        39.8148,
        -76.1959
      ],
      [
        39.2934,
        -77.0686
      ],
      [
        38.3647,
        -79.2603
      ],
      [
        37.3492,
        -81.4947
      ],
      [
        36.6617,
        -82.925
      ],
      [
        36.2126,
        -83.8274
      ],
      [
        35.7961,
        -84.6437
      ],
      [
        34.7625,
        -86.4056
      ],
      [
        32.9599,
        -89.0747
      ]
    ]
  },
  {
    "hex": "06a001",
    "name": "Qatar Amiri Flight",
    "category": "Dictator Alert",
    "callsign": "A7HHK",
    "lon": -1.3154,
    "lat": 52.8281,
    "alt": null,
    "velocity": 0,
    "heading": 132.19,
    "trace": [
      [
        41.5405,
        30.4921
      ],
      [
        42.1811,
        29.123
      ],
      [
        43.086,
        27.645
      ],
      [
        43.2229,
        27.4121
      ],
      [
        44.1818,
        25.7461
      ],
      [
        44.7169,
        24.7686
      ],
      [
        46.3371,
        21.5943
      ],
      [
        47.4216,
        18.1229
      ],
      [
        48.0467,
        16.0821
      ],
      [
        48.4711,
        14.7191
      ],
      [
        49.4516,
        11.3521
      ],
      [
        50.39,
        7.6518
      ],
      [
        50.8962,
        5.2316
      ],
      [
        51.1841,
        3.6373
      ],
      [
        51.4852,
        2.1665
      ],
      [
        52.3288,
        -0.7159
      ],
      [
        52.8281,
        -1.3154
      ]
    ]
  },
  {
    "hex": "ab7437",
    "name": "Global Crossing Airlines",
    "category": "Hired Gun",
    "callsign": "GXA6183",
    "lon": -80.2931,
    "lat": 25.9124,
    "alt": -15.24,
    "velocity": 61.84,
    "heading": 86.66,
    "trace": [
      [
        27.4727,
        -96.8246
      ],
      [
        28.7782,
        -94.5401
      ],
      [
        29.1682,
        -93.1236
      ],
      [
        29.0231,
        -92.0776
      ],
      [
        28.6576,
        -89.6711
      ],
      [
        28.1597,
        -87.2672
      ],
      [
        27.7202,
        -85.7719
      ],
      [
        27.4931,
        -84.7787
      ],
      [
        27.327,
        -83.8617
      ],
      [
        26.6406,
        -81.968
      ],
      [
        25.9124,
        -80.2931
      ]
    ]
  },
  {
    "hex": "710125",
    "name": "Gov of Saudi Arabia",
    "category": "Dictator Alert",
    "callsign": "SVA7148",
    "lon": -2.1819,
    "lat": 42.8727,
    "alt": 10668,
    "velocity": 250.68,
    "heading": 111.3,
    "trace": [
      [
        44.8318,
        -10.272
      ],
      [
        44.5737,
        -9.014
      ],
      [
        43.9534,
        -6.2784
      ],
      [
        42.8727,
        -2.1819
      ]
    ]
  }
]