[
  {
    "hex": "a0d062",
    "name": "Atlas Air",
    "category": "Hired Gun",
    "callsign": "GTI8835",
    "lon": -84.7936,
    "lat": 38.9359,
    "alt": 3810,
    "velocity": 207.73,
    "heading": 98.83,
    "trace": [
      [
        38.9359,
        -84.7936
      ]
    ]
  },
  {
    "hex": "a2c4e0",
    "name": "Global Crossing Airlines",
    "category": "Hired Gun",
    "callsign": "GXA6164",
    "lon": -93.8577,
    "lat": 30.0361,
    "alt": 10386.06,
    "velocity": 244.91,
    "heading": 40.31,
    "trace": [
      [
        27.1709,
        -96.8311
      ],
      [
        30.0361,
        -93.8577
      ]
    ]
  },
  {
    "hex": "a2d615",
    "name": "Global Crossing Airlines",
    "category": "Hired Gun",
    "callsign": "GXA4627",
    "lon": -78.7839,
    "lat": 35.8784,
    "alt": null,
    "velocity": 3.09,
    "heading": 331.88,
    "trace": [
      [
        33.5153,
        -83.649
      ],
      [
        34.5346,
        -80.1821
      ],
      [
        35.8784,
        -78.7839
      ]
    ]
  },
  {
    "hex": "a756eb",
    "name": "Meta Aerospace",
    "category": "Hired Gun",
    "callsign": "SWB47",
    "lon": 138.5164,
    "lat": 35.4665,
    "alt": 4953,
    "velocity": 177.41,
    "heading": 52.07,
    "trace": [
      [
        35.4665,
        138.5164
      ]
    ]
  },
  {
    "hex": "a9c52e",
    "name": "National Airlines",
    "category": "Hired Gun",
    "callsign": "NCR838",
    "lon": -3.4048,
    "lat": 55.9942,
    "alt": 9753.6,
    "velocity": 282.36,
    "heading": 301.89,
    "trace": [
      [
        45.3228,
        7.9078
      ],
      [
        50.6068,
        5.1037
      ],
      [
        53.5571,
        2.7491
      ],
      [
        55.9942,
        -3.4048
      ]
    ]
  },
  {
    "hex": "710100",
    "name": "Saudi Ministry of Finance",
    "category": "Dictator Alert",
    "callsign": "SVA993",
    "lon": 49.6923,
    "lat": 23.2186,
    "alt": 10363.2,
    "velocity": 209.04,
    "heading": 285.27,
    "trace": [
      [
        23.0315,
        55.9113
      ],
      [
        22.8133,
        52.99
      ],
      [
        23.2186,
        49.6923
      ]
    ]
  },
  {
    "hex": "a6b0f5",
    "name": "Global Crossing Airlines",
    "category": "Hired Gun",
    "callsign": "GXA6153",
    "lon": -104.56,
    "lat": 30.9915,
    "alt": 9982.2,
    "velocity": 257.45,
    "heading": 111.7,
    "trace": [
      [
        30.9915,
        -104.56
      ]
    ]
  }
]