[
  {
    "hex": "a49951",
    "name": "Amerijet International",
    "category": "Hired Gun",
    "callsign": "AJT1330",
    "lon": -80.0131,
    "lat": 27.8774,
    "alt": 10980.42,
    "velocity": 276.38,
    "heading": 152.15,
    "trace": [
      [
        37.3217,
        -85.2907
      ],
      [
        34.3238,
        -82.5509
      ],
      [
        32.3672,
        -81.3698
      ],
      [
        27.8774,
        -80.0131
      ]
    ]
  },
  {
    "hex": "ab9639",
    "name": "Omni Air International",
    "category": "Hired Gun",
    "callsign": "CMB554",
    "lon": 23.0173,
    "lat": 42.3983,
    "alt": 11582.4,
    "velocity": 269.09,
    "heading": 42.44,
    "trace": [
      [
        42.3983,
        23.0173
      ]
    ]
  },
  {
    "hex": "78048c",
    "name": "Gov of PRC",
    "category": "Dictator Alert",
    "callsign": "CCA838",
    "lon": 17.7996,
    "lat": 50.7896,
    "alt": 10668,
    "velocity": 238.71,
    "heading": 40.28,
    "trace": [
      [
        45.6223,
        8.7215
      ],
      [
        46.2139,
        11.2749
      ],
      [
        47.6485,
        13.3442
      ],
      [
        50.7896,
        17.7996
      ]
    ]
  },
  {
    "hex": "a2f016",
    "name": "Global Crossing Airlines",
    "category": "Hired Gun",
    "callsign": "GXA107",
    "lon": -82.322,
    "lat": 28.349,
    "alt": 9677.4,
    "velocity": 199.26,
    "heading": 324.67,
    "trace": [
      [
        25.8242,
        -80.1632
      ],
      [
        28.349,
        -82.322
      ]
    ]
  },
  {
    "hex": "a815bf",
    "name": "Dynamic Avlease Inc",
    "category": "Hired Gun",
    "callsign": "N62V",
    "lon": -95.5263,
    "lat": 18.7209,
    "alt": 3596.64,
    "velocity": 100.59,
    "heading": 303.53,
    "trace": [
      [
        18.7209,
        -95.5263
      ]
    ]
  }
]