[
  {
    "hex": "a808d5",
    "name": "Airborne Tactical Advantage",
    "category": "Hired Gun",
    "callsign": "ATAC41",
    "lon": -112.6277,
    "lat": 33.2978,
    "alt": 1386.84,
    "velocity": 173.43,
    "heading": 10.94,
    "trace": [
      [
        32.3894,
        -112.8778
      ],
      [
        33.2978,
        -112.6277
      ]
    ]
  },
  {
    "hex": "c070d7",
    "name": "Top Aces Inc",
    "category": "Hired Gun",
    "callsign": "CHETA73",
    "lon": -82.166,
    "lat": 26.1516,
    "alt": 4518.66,
    "velocity": 158.84,
    "heading": 165.56,
    "trace": [
      [
        26.1516,
        -82.166
      ]
    ]
  },
  {
    "hex": "abfbb7",
    "name": "Top Aces Inc",
    "category": "Hired Gun",
    "callsign": "ACES1",
    "lon": -112.5768,
    "lat": 33.444,
    "alt": 1249.68,
    "velocity": 162.08,
    "heading": 31.37,
    "trace": [
      [
        31.9345,
        -112.4185
      ],
      [
        33.444,
        -112.5768
      ]
    ]
  },
  {
    "hex": "a3db1c",
    "name": "Airborne Tactical Advantage",
    "category": "Hired Gun",
    "callsign": "N348AX",
    "lon": -79.2578,
    "lat": 31.8317,
    "alt": 7155.18,
    "velocity": 250.18,
    "heading": 69.66,
    "trace": [
      [
        32.2271,
        -79.2409
      ],
      [
        31.8317,
        -79.2578
      ]
    ]
  },
  {
    "hex": "4009ce",
    "name": "Draken Europe",
    "category": "Hired Gun",
    "callsign": "ZODIAC12",
    "lon": -1.4373,
    "lat": 54.5061,
    "alt": null,
    "velocity": 2.31,
    "heading": 331.88,
    "trace": [
      [
        54.7582,
        -0.6232
      ],
      [
        54.4915,
        -0.192
      ],
      [
        54.5061,
        -1.4373
      ]
    ]
  },
  {
    "hex": "4009ca",
    "name": "Draken Europe",
    "category": "Hired Gun",
    "callsign": "BRMDE11",
    "lon": -1.4373,
    "lat": 54.506,
    "alt": null,
    "velocity": 6.43,
    "heading": 334.69,
    "trace": [
      [
        55.1613,
        0.0619
      ],
      [
        55.0735,
        0.4143
      ],
      [
        54.506,
        -1.4373
      ]
    ]
  },
  {
    "hex": "a86908",
    "name": "Airborne Tactical Advantage",
    "category": "Hired Gun",
    "callsign": "ATAC42",
    "lon": -112.3829,
    "lat": 33.53,
    "alt": null,
    "velocity": 11.83,
    "heading": 42.19,
    "trace": [
      [
        32.3525,
        -112.8084
      ],
      [
        33.53,
        -112.3829
      ]
    ]
  },
  {
    "hex": "a7f9f9",
    "name": "Airborne Tactical Advantage",
    "category": "Hired Gun",
    "callsign": "ATAC1",
    "lon": -76.5907,
    "lat": 35.1886,
    "alt": 7200.9,
    "velocity": 205.16,
    "heading": 15.12,
    "trace": [
      [
        35.1886,
        -76.5907
      ]
    ]
  },
  {
    "hex": "a16971",
    "name": "Phoenix Air",
    "category": "Hired Gun",
    "callsign": "GRB078",
    "lon": -94.8566,
    "lat": 34.5288,
    "alt": 12199.62,
    "velocity": 209.87,
    "heading": 273.94,
    "trace": [
      [
        33.9145,
        -84.2801
      ],
      [
        34.1138,
        -89.6259
      ],
      [
        34.5288,
        -94.8566
      ]
    ]
  },
  {
    "hex": "a395e5",
    "name": "Airborne Tactical Advantage",
    "category": "Hired Gun",
    "callsign": "N330AX",
    "lon": -98.3808,
    "lat": 32.0564,
    "alt": 3337.56,
    "velocity": 169.47,
    "heading": 52.4,
    "trace": [
      [
        32.7742,
        -97.3414
      ],
      [
        31.5808,
        -100.1248
      ],
      [
        32.0564,
        -98.3808
      ]
    ]
  },
  {
    "hex": "a2d615",
    "name": "Global Crossing Airlines",
    "category": "Hired Gun",
    "callsign": "GXA620",
    "lon": -75.983,
    "lat": 40.2647,
    "alt": 10972.8,
    "velocity": 200.63,
    "heading": 238.63,
    "trace": [
      [
        42.4256,
        -71.4294
      ],
      [
        40.2647,
        -75.983
      ]
    ]
  },
  {
    "hex": "a75013",
    "name": "Global Crossing Airlines",
    "category": "Hired Gun",
    "callsign": "GXA6226",
    "lon": -109.9454,
    "lat": 29.5456,
    "alt": 10058.4,
    "velocity": 242.12,
    "heading": 121.8,
    "trace": [
      [
        32.8732,
        -117.1379
      ],
      [
        31.9134,
        -114.5835
      ],
      [
        29.5456,
        -109.9454
      ]
    ]
  },
  {
    "hex": "c0871c",
    "name": "Top Aces Inc",
    "category": "Hired Gun",
    "callsign": "CHETA71",
    "lon": -82.0989,
    "lat": 25.9835,
    "alt": 5113.02,
    "velocity": 163.66,
    "heading": 159,
    "trace": [
      [
        25.9835,
        -82.0989
      ]
    ]
  },
  {
    "hex": "c0792f",
    "name": "Top Aces Inc",
    "category": "Hired Gun",
    "callsign": "BRUSR01",
    "lon": -102.1765,
    "lat": 35.0847,
    "alt": 4831.08,
    "velocity": 173.68,
    "heading": 233.67,
    "trace": [
      [
        35.0847,
        -102.1765
      ]
    ]
  },
  {
    "hex": "aacff9",
    "name": "Tactical Air Support",
    "category": "Hired Gun",
    "callsign": "VILLN91",
    "lon": -115.3877,
    "lat": 35.5454,
    "alt": 5288.28,
    "velocity": 242.35,
    "heading": 60.5,
    "trace": [
      [
        35.5454,
        -115.3877
      ]
    ]
  },
  {
    "hex": "a3c11b",
    "name": "Airborne Tactical Advantage",
    "category": "Hired Gun",
    "callsign": "N341AX",
    "lon": -78.784,
    "lat": 32.1779,
    "alt": 9700.26,
    "velocity": 234.72,
    "heading": 94.27,
    "trace": [
      [
        36.4084,
        -77.1429
      ],
      [
        32.2471,
        -79.2276
      ],
      [
        32.1779,
        -78.784
      ]
    ]
  },
  {
    "hex": "a7fdb0",
    "name": "Airborne Tactical Advantage",
    "category": "Hired Gun",
    "callsign": "VIPER1",
    "lon": -97.3274,
    "lat": 32.9771,
    "alt": 472.44,
    "velocity": 101,
    "heading": 243.04,
    "trace": [
      [
        31.6864,
        -100.215
      ],
      [
        32.9771,
        -97.3274
      ]
    ]
  },
  {
    "hex": "a86cbf",
    "name": "Airborne Tactical Advantage",
    "category": "Hired Gun",
    "callsign": "ATAC4",
    "lon": -76.9197,
    "lat": 34.7559,
    "alt": 6111.24,
    "velocity": 241.51,
    "heading": 337.59,
    "trace": [
      [
        34.7559,
        -76.9197
      ]
    ]
  },
  {
    "hex": "a384b0",
    "name": "Airborne Tactical Advantage",
    "category": "Hired Gun",
    "callsign": "N326AX",
    "lon": -97.8822,
    "lat": 32.5922,
    "alt": 3169.92,
    "velocity": 157.73,
    "heading": 36.65,
    "trace": [
      [
        31.5972,
        -100.13
      ],
      [
        32.5922,
        -97.8822
      ]
    ]
  }
]