[
  {
    "hex": "ad3c48",
    "name": "National Airlines",
    "category": "Hired Gun",
    "callsign": "NCR848",
    "lon": -83.802,
    "lat": 34.4803,
    "alt": 5013.96,
    "velocity": 152.81,
    "heading": 205.1,
    "trace": [
      [
        48.9554,
        -77.3843
      ],
      [
        48.1904,
        -78.1517
      ],
      [
        47.4902,
        -78.8301
      ],
      [
        46.8206,
        -79.4586
      ],
      [
        43.2838,
        -82.4939
      ],
      [
        38.7464,
        -83.7111
      ],
      [
        35.4521,
        -83.2483
      ],
      [
        34.4803,
        -83.802
      ]
    ]
  },
  {
    "hex": "a2c129",
    "name": "Global Crossing Airlines",
    "category": "Hired Gun",
    "callsign": "GXA6110",
    "lon": -88.0874,
    "lat": 31.0158,
    "alt": 10050.78,
    "velocity": 262.98,
    "heading": 96.4,
    "trace": [
      [
        31.1927,
        -90.1144
      ],
      [
        31.0158,
        -88.0874
      ]
    ]
  },
  {
    "hex": "89607a",
    "name": "Dubai Air Wing",
    "category": "Dictator Alert",
    "callsign": "DUB6",
    "lon": 17.7009,
    "lat": 46.6955,
    "alt": 11582.4,
    "velocity": 235.39,
    "heading": 286.38,
    "trace": [
      [
        41.9151,
        32.2816
      ],
      [
        44.7219,
        24.7984
      ],
      [
        46.2348,
        19.8613
      ],
      [
        46.6955,
        17.7009
      ]
    ]
  },
  {
    "hex": "a0f8f9",
    "name": "Atlas Air",
    "category": "Hired Gun",
    "callsign": "FDX619",
    "lon": -84.1351,
    "lat": 30.5524,
    "alt": 10972.8,
    "velocity": 237.38,
    "heading": 323.73,
    "trace": [
      [
        26.1767,
        -80.6239
      ],
      [
        29.2869,
        -83.0816
      ],
      [
        30.5524,
        -84.1351
      ]
    ]
  },
  {
    "hex": "70c0b3",
    "name": "Oman Royal Flight",
    "category": "Dictator Alert",
    "callsign": "ORF3",
    "lon": 18.8077,
    "lat": 47.5476,
    "alt": 12192,
    "velocity": 254.45,
    "heading": 301.44,
    "trace": [
      [
        41.3479,
        30.899
      ],
      [
        44.323,
        25.5998
      ],
      [
        46.6569,
        20.892
      ],
      [
        47.5476,
        18.8077
      ]
    ]
  },
  {
    "hex": "a0c62d",
    "name": "Eastern Air Express",
    "category": "Hired Gun",
    "callsign": "BBQ702",
    "lon": -80.5553,
    "lat": 25.6954,
    "alt": 3268.98,
    "velocity": 169.1,
    "heading": 63.82,
    "trace": [
      [
        24.6246,
        -81.6049
      ],
      [
        25.6954,
        -80.5553
      ]
    ]
  },
  {
    "hex": "acfc26",
    "name": "National Airlines",
    "category": "Hired Gun",
    "callsign": "CMB579",
    "lon": -89.3535,
    "lat": 45.5873,
    "alt": 12496.8,
    "velocity": 280.14,
    "heading": 122.55,
    "trace": [
      [
        54.9476,
        -112.7022
      ],
      [
        52.8155,
        -104.5557
      ],
      [
        49.6215,
        -96.942
      ],
      [
        46.5796,
        -91.6583
      ],
      [
        45.5873,
        -89.3535
      ]
    ]
  },
  {
    "hex": "a86e85",
    "name": "Global Crossing Airlines",
    "category": "Hired Gun",
    "callsign": "GXA200",
    "lon": -80.4001,
    "lat": 25.775,
    "alt": 800.1,
    "velocity": 125.78,
    "heading": 228.81,
    "trace": [
      [
        25.775,
        -80.4001
      ]
    ]
  },
  {
    "hex": "ad7274",
    "name": "Global Crossing Airlines",
    "category": "Hired Gun",
    "callsign": "GXA6121",
    "lon": -89.9729,
    "lat": 18.6801,
    "alt": 10050.78,
    "velocity": 222.57,
    "heading": 187.44,
    "trace": [
      [
        19.7936,
        -89.8178
      ],
      [
        18.6801,
        -89.9729
      ]
    ]
  },
  {
    "hex": "06a038",
    "name": "Qatar Amiri Flight",
    "category": "Dictator Alert",
    "callsign": "QAF4",
    "lon": 2.0967,
    "lat": 48.7177,
    "alt": 1165.86,
    "velocity": 118.62,
    "heading": 240.66,
    "trace": [
      [
        48.7177,
        2.0967
      ]
    ]
  },
  {
    "hex": "ab7437",
    "name": "Global Crossing Airlines",
    "category": "Hired Gun",
    "callsign": "GXA6181",
    "lon": -84.7927,
    "lat": 27.8049,
    "alt": 11574.78,
    "velocity": 196.25,
    "heading": 280.57,
    "trace": [
      [
        25.9372,
        -80.3535
      ],
      [
        27.5484,
        -83.3319
      ],
      [
        27.8049,
        -84.7927
      ]
    ]
  },
  {
    "hex": "710125",
    "name": "Gov of Saudi Arabia",
    "category": "Dictator Alert",
    "callsign": "SVA7135",
    "lon": 16.4509,
    "lat": 45.1897,
    "alt": 11582.4,
    "velocity": 241.43,
    "heading": 308.95,
    "trace": [
      [
        34.6764,
        27.661
      ],
      [
        37.8719,
        25.2481
      ],
      [
        41.4736,
        21.7612
      ],
      [
        44.1762,
        18.1747
      ],
      [
        45.1897,
        16.4509
      ]
    ]
  }
]