[
  {
    "hex": "a0d062",
    "name": "Atlas Air",
    "category": "Hired Gun",
    "callsign": "GTI774",
    "lon": -79.9346,
    "lat": 25.5753,
    "alt": 3566.16,
    "velocity": 162.44,
    "heading": 312.18,
    "trace": [
      [
        25.5753,
        -79.9346
      ]
    ]
  },
  {
    "hex": "a1f3aa",
    "name": "Omni Air International",
    "category": "Hired Gun",
    "callsign": "CMB592",
    "lon": 16.0511,
    "lat": 51.0947,
    "alt": 12496.8,
    "velocity": 251.87,
    "heading": 107.47,
    "trace": [
      [
        51.0947,
        16.0511
      ]
    ]
  },
  {
    "hex": "a3defb",
    "name": "Amerijet International",
    "category": "Hired Gun",
    "callsign": "AJT8543",
    "lon": -71.1068,
    "lat": 20.2987,
    "alt": 10668,
    "velocity": 245.37,
    "heading": 141.64,
    "trace": [
      [
        20.2987,
        -71.1068
      ]
    ]
  },
  {
    "hex": "6830ed",
    "name": "Gov of Kazakhstan",
    "category": "Dictator Alert",
    "callsign": "BEC006",
    "lon": 7.5133,
    "lat": 47.6171,
    "alt": null,
    "velocity": 4.37,
    "heading": 334.69,
    "trace": [
      [
        47.6171,
        7.5133
      ]
    ]
  },
  {
    "hex": "a7a2be",
    "name": "ISR Platforms",
    "category": "Hired Gun",
    "callsign": "",
    "lon": 127.765,
    "lat": 37.6958,
    "alt": 11582.4,
    "velocity": 230.76,
    "heading": 63.09,
    "trace": [
      [
        37.239,
        125.424
      ],
      [
        37.4005,
        127.0357
      ],
      [
        37.6958,
        127.765
      ]
    ]
  },
  {
    "hex": "406d27",
    "name": "AirTanker",
    "category": "Hired Gun",
    "callsign": "EXS9TL",
    "lon": -0.6136,
    "lat": 46.2104,
    "alt": 11887.2,
    "velocity": 236.94,
    "heading": 159.01,
    "trace": [
      [
        46.2104,
        -0.6136
      ]
    ]
  },
  {
    "hex": "c088a9",
    "name": "Top Aces Inc",
    "category": "Hired Gun",
    "callsign": "AMBUSH1",
    "lon": 8.8392,
    "lat": 53.392,
    "alt": 571.5,
    "velocity": 139.8,
    "heading": 9.53,
    "trace": [
      [
        53.392,
        8.8392
      ]
    ]
  },
  {
    "hex": "406e9f",
    "name": "AirTanker",
    "category": "Hired Gun",
    "callsign": "EXS22RB",
    "lon": -6.7251,
    "lat": 42.6499,
    "alt": 12496.8,
    "velocity": 225.21,
    "heading": 202.99,
    "trace": [
      [
        42.6499,
        -6.7251
      ]
    ]
  },
  {
    "hex": "3cd067",
    "name": "Gesellschaft fur Flugzieldarstellung",
    "category": "Hired Gun",
    "callsign": "GFD1",
    "lon": 10.8885,
    "lat": 53.9764,
    "alt": 1615.44,
    "velocity": 124.24,
    "heading": 117.1,
    "trace": [
      [
        53.9764,
        10.8885
      ]
    ]
  },
  {
    "hex": "a9c52e",
    "name": "National Airlines",
    "category": "Hired Gun",
    "callsign": "NCR810",
    "lon": -79.1599,
    "lat": 44.933,
    "alt": 10058.4,
    "velocity": 273.68,
    "heading": 60.5,
    "trace": [
      [
        44.933,
        -79.1599
      ]
    ]
  },
  {
    "hex": "4009d6",
    "name": "Draken Europe",
    "category": "Hired Gun",
    "callsign": "TASMAN01",
    "lon": -0.6041,
    "lat": 53.9938,
    "alt": 5295.9,
    "velocity": 152.4,
    "heading": 138.83,
    "trace": [
      [
        53.9938,
        -0.6041
      ]
    ]
  },
  {
    "hex": "4009d1",
    "name": "Draken Europe",
    "category": "Hired Gun",
    "callsign": "CRIMSON2",
    "lon": -1.7789,
    "lat": 50.8267,
    "alt": 990.6,
    "velocity": 117.35,
    "heading": 282.15,
    "trace": [
      [
        50.8267,
        -1.7789
      ]
    ]
  },
  {
    "hex": "a95c2f",
    "name": "National Airlines",
    "category": "Hired Gun",
    "callsign": "NCR809",
    "lon": -87.4869,
    "lat": 36.3505,
    "alt": 11582.4,
    "velocity": 240.72,
    "heading": 220.84,
    "trace": [
      [
        36.3505,
        -87.4869
      ]
    ]
  }
]