[
  {
    "hex": "a95c2f",
    "name": "National Airlines",
    "category": "Hired Gun",
    "callsign": "NCR845",
    "lon": -106.1775,
    "lat": 33.2765,
    "alt": 12192,
    "velocity": 228.89,
    "heading": 277.62,
    "trace": [
      [
        28.049,
        -83.6333
      ],
      [
        30.8459,
        -92.9329
      ],
      [
        30.9743,
        -93.417
      ],
      [
        31.9481,
        -97.3928
      ],
      [
        32.4975,
        -100.452
      ],
      [
        32.982,
        -103.766
      ],
      [
        33.1699,
        -105.2578
      ],
      [
        33.2765,
        -106.1775
      ]
    ]
  },
  {
    "hex": "a2d25e",
    "name": "Global Crossing Airlines",
    "category": "Hired Gun",
    "callsign": "GXA1662",
    "lon": -73.6631,
    "lat": 25.1768,
    "alt": 11590.02,
    "velocity": 208.53,
    "heading": 311.2,
    "trace": [
      [
        22.2033,
        -69.8547
      ],
      [
        23.9665,
        -72.1083
      ],
      [
        24.71,
        -73.0798
      ],
      [
        25.1768,
        -73.6631
      ]
    ]
  },
  {
    "hex": "a451cb",
    "name": "Amerijet International",
    "category": "Hired Gun",
    "callsign": "AJT8241",
    "lon": -69.9772,
    "lat": 14.1468,
    "alt": 12192,
    "velocity": 217.44,
    "heading": 234.24,
    "trace": [
      [
        14.1468,
        -69.9772
      ]
    ]
  },
  {
    "hex": "406b79",
    "name": "AirTanker",
    "category": "Hired Gun",
    "callsign": "TOW2231",
    "lon": -6.3403,
    "lat": 45.9627,
    "alt": 12192,
    "velocity": 209.35,
    "heading": 23.92,
    "trace": [
      [
        39.3682,
        -10.1566
      ],
      [
        41.8936,
        -9.3703
      ],
      [
        44.2435,
        -7.4395
      ],
      [
        45.3064,
        -6.7538
      ],
      [
        45.9627,
        -6.3403
      ]
    ]
  },
  {
    "hex": "ab7437",
    "name": "Global Crossing Airlines",
    "category": "Hired Gun",
    "callsign": "GXA6143",
    "lon": -101.0458,
    "lat": 29.5642,
    "alt": 11894.82,
    "velocity": 248.65,
    "heading": 130.05,
    "trace": [
      [
        32.687,
        -109.9029
      ],
      [
        31.8862,
        -106.5701
      ],
      [
        30.9646,
        -103.0351
      ],
      [
        30.1003,
        -101.7801
      ],
      [
        29.5642,
        -101.0458
      ]
    ]
  },
  {
    "hex": "710100",
    "name": "Saudi Ministry of Finance",
    "category": "Dictator Alert",
    "callsign": "SVA931",
    "lon": 23.0106,
    "lat": 37.8718,
    "alt": 9753.6,
    "velocity": 243.58,
    "heading": 320.05,
    "trace": [
      [
        36.1599,
        24.7586
      ],
      [
        37.2288,
        23.6795
      ],
      [
        37.8718,
        23.0106
      ]
    ]
  },
  {
    "hex": "a87876",
    "name": "Atlas Air",
    "category": "Hired Gun",
    "callsign": "GTI8290",
    "lon": 137.8772,
    "lat": 35.5291,
    "alt": 7581.9,
    "velocity": 253.55,
    "heading": 83.83,
    "trace": [
      [
        35.8867,
        129.532
      ],
      [
        35.513,
        134.719
      ],
      [
        35.4162,
        136.7063
      ],
      [
        35.5291,
        137.8772
      ]
    ]
  },
  {
    "hex": "acb84d",
    "name": "National Airlines",
    "category": "Hired Gun",
    "callsign": "NCR590",
    "lon": 88.6386,
    "lat": 22.2364,
    "alt": 11361.42,
    "velocity": 267.47,
    "heading": 38.13,
    "trace": [
      [
        17.6943,
        84.7683
      ],
      [
        20.3042,
        87.0378
      ],
      [
        21.4992,
        88.0219
      ],
      [
        22.2364,
        88.6386
      ]
    ]
  }
]