[
  {
    "hex": "a2f9dd",
    "name": "Global Crossing Airlines",
    "category": "Hired Gun",
    "callsign": "GXA610",
    "lon": -98.0803,
    "lat": 31.8614,
    "alt": 9448.8,
    "velocity": 240.37,
    "heading": 29.91,
    "trace": [
      [
        31.8614,
        -98.0803
      ]
    ]
  },
  {
    "hex": "a83f98",
    "name": "Global Crossing Airlines",
    "category": "Hired Gun",
    "callsign": "GXA4635",
    "lon": -96.5143,
    "lat": 40.8989,
    "alt": 3268.98,
    "velocity": 172.46,
    "heading": 112.82,
    "trace": [
      [
        40.8989,
        -96.5143
      ]
    ]
  },
  {
    "hex": "a0f8f9",
    "name": "Atlas Air",
    "category": "Hired Gun",
    "callsign": "GTI765",
    "lon": -90.2357,
    "lat": 35.9281,
    "alt": 11285.22,
    "velocity": 267.16,
    "heading": 55.12,
    "trace": [
      [
        35.9281,
        -90.2357
      ]
    ]
  },
  {
    "hex": "a451cb",
    "name": "Amerijet International",
    "category": "Hired Gun",
    "callsign": "AJT8346",
    "lon": -73.1615,
    "lat": 21.5152,
    "alt": 10988.04,
    "velocity": 190.35,
    "heading": 303.09,
    "trace": [
      [
        21.5152,
        -73.1615
      ]
    ]
  },
  {
    "hex": "a97a1a",
    "name": "ISR Platforms",
    "category": "Hired Gun",
    "callsign": "TGR671",
    "lon": 121.8379,
    "lat": 13.8456,
    "alt": 3352.8,
    "velocity": 81.3,
    "heading": 131.15,
    "trace": [
      [
        13.8456,
        121.8379
      ]
    ]
  },
  {
    "hex": "a86e85",
    "name": "Global Crossing Airlines",
    "category": "Hired Gun",
    "callsign": "GXA6143",
    "lon": -100.7562,
    "lat": 29.3327,
    "alt": 10668,
    "velocity": 254.93,
    "heading": 140.98,
    "trace": [
      [
        26.3367,
        -80.8844
      ],
      [
        27.6809,
        -84.0701
      ],
      [
        28.8251,
        -88.4916
      ],
      [
        29.3038,
        -91.0032
      ],
      [
        31.495,
        -105.0859
      ],
      [
        29.3327,
        -100.7562
      ]
    ]
  }
]