[
  {
    "hex": "406d27",
    "name": "AirTanker",
    "category": "Hired Gun",
    "callsign": "TOW2231",
    "lon": -3.305,
    "lat": 50.7656,
    "alt": 7239,
    "velocity": 186.41,
    "heading": 27.98,
    "trace": [
      [
        40.4794,
        -9.8107
      ],
      [
        44.5726,
        -7.1733
      ],
      [
        46.9241,
        -5.6974
      ],
      [
        49.6176,
        -3.8217
      ],
      [
        50.7656,
        -3.305
      ]
    ]
  },
  {
    "hex": "acb84d",
    "name": "National Airlines",
    "category": "Hired Gun",
    "callsign": "CMB529",
    "lon": 0.535,
    "lat": 61.7382,
    "alt": 10668,
    "velocity": 272.55,
    "heading": 136.45,
    "trace": [
      [
        61.7382,
        0.535
      ]
    ]
  },
  {
    "hex": "157712",
    "name": "Russia Special Flight Detachment",
    "category": "Dictator Alert",
    "callsign": "RSD532",
    "lon": 37.5959,
    "lat": 55.4641,
    "alt": 3322.32,
    "velocity": 2.06,
    "heading": 0,
    "trace": [
      [
        55.4641,
        37.5959
      ]
    ]
  }
]