[
  {
    "hex": "a0d062",
    "name": "Atlas Air",
    "category": "Hired Gun",
    "callsign": "GTI9123",
    "lon": -90.9101,
    "lat": 34.5662,
    "alt": 7856.22,
    "velocity": 216.46,
    "heading": 224.33,
    "trace": [
      [
        35.034,
        -90.272
      ],
      [
        34.5662,
        -90.9101
      ]
    ]
  },
  {
    "hex": "abfbb7",
    "name": "Top Aces Inc",
    "category": "Hired Gun",
    "callsign": "ACES1",
    "lon": -112.6174,
    "lat": 33.1353,
    "alt": 1371.6,
    "velocity": 171.07,
    "heading": 328.65,
    "trace": [
      [
        33.5987,
        -112.4989
      ],
      [
        31.9918,
        -111.7636
      ],
      [
        32.3271,
        -112.4238
      ],
      [
        32.3632,
        -112.5978
      ],
      [
        32.5156,
        -112.2484
      ],
      [
        33.1353,
        -112.6174
      ]
    ]
  },
  {
    "hex": "a49951",
    "name": "Amerijet International",
    "category": "Hired Gun",
    "callsign": "AJT723",
    "lon": -81.261,
    "lat": 24.5227,
    "alt": 10378.44,
    "velocity": 222.75,
    "heading": 244.56,
    "trace": [
      [
        25.8053,
        -80.2615
      ],
      [
        24.914,
        -80.5452
      ],
      [
        24.5227,
        -81.261
      ]
    ]
  },
  {
    "hex": "ad5ff9",
    "name": "IBC Airways",
    "category": "Hired Gun",
    "callsign": "",
    "lon": -81.0473,
    "lat": 25.2172,
    "alt": 2621.28,
    "velocity": 133.65,
    "heading": 8.41,
    "trace": [
      [
        25.2172,
        -81.0473
      ]
    ]
  },
  {
    "hex": "a81043",
    "name": "Airborne Tactical Advantage",
    "category": "Hired Gun",
    "callsign": "ATAC11",
    "lon": -112.6991,
    "lat": 33.716,
    "alt": 4747.26,
    "velocity": 229.13,
    "heading": 286.97,
    "trace": [
      [
        33.716,
        -112.6991
      ]
    ]
  },
  {
    "hex": "896430",
    "name": "Dubai Air Wing",
    "category": "Dictator Alert",
    "callsign": "DUB9",
    "lon": 53.9172,
    "lat": 26.1298,
    "alt": 7620,
    "velocity": 217.03,
    "heading": 145.82,
    "trace": [
      [
        28.7731,
        52.8058
      ],
      [
        27.5665,
        53.133
      ],
      [
        26.7685,
        53.3961
      ],
      [
        26.1298,
        53.9172
      ]
    ]
  },
  {
    "hex": "a3defb",
    "name": "Amerijet International",
    "category": "Hired Gun",
    "callsign": "AJT830",
    "lon": -72.1784,
    "lat": 21.4921,
    "alt": 11582.4,
    "velocity": 220.81,
    "heading": 298.83,
    "trace": [
      [
        20.7116,
        -70.6853
      ],
      [
        21.1092,
        -71.4408
      ],
      [
        21.4921,
        -72.1784
      ]
    ]
  },
  {
    "hex": "a2d615",
    "name": "Global Crossing Airlines",
    "category": "Hired Gun",
    "callsign": "GXA1606",
    "lon": -94.036,
    "lat": 42.0949,
    "alt": 11590.02,
    "velocity": 203.23,
    "heading": 270.87,
    "trace": [
      [
        41.8753,
        -88.3538
      ],
      [
        42.0718,
        -90.5942
      ],
      [
        42.0868,
        -92.0862
      ],
      [
        42.0886,
        -93.0847
      ],
      [
        42.0949,
        -94.036
      ]
    ]
  },
  {
    "hex": "a75013",
    "name": "Global Crossing Airlines",
    "category": "Hired Gun",
    "callsign": "GXA6144",
    "lon": -98.6274,
    "lat": 26.6072,
    "alt": 5562.6,
    "velocity": 222.47,
    "heading": 141.2,
    "trace": [
      [
        31.6433,
        -106.1383
      ],
      [
        31.3772,
        -105.2654
      ],
      [
        30.6105,
        -102.4923
      ],
      [
        29.0863,
        -100.5705
      ],
      [
        28.0031,
        -99.7895
      ],
      [
        27.2722,
        -99.229
      ],
      [
        26.6072,
        -98.6274
      ]
    ]
  },
  {
    "hex": "a451cb",
    "name": "Amerijet International",
    "category": "Hired Gun",
    "callsign": "AJT880",
    "lon": -72.6937,
    "lat": 38.245,
    "alt": 10972.8,
    "velocity": 219,
    "heading": 328.25,
    "trace": [
      [
        37.5892,
        -72.1827
      ],
      [
        38.245,
        -72.6937
      ]
    ]
  },
  {
    "hex": "c0793d",
    "name": "Top Aces Inc",
    "category": "Hired Gun",
    "callsign": "BRUSR01",
    "lon": -106.0056,
    "lat": 50.57,
    "alt": 10660.38,
    "velocity": 255.15,
    "heading": 81.89,
    "trace": [
      [
        48.7034,
        -123.1662
      ],
      [
        48.9641,
        -122.179
      ],
      [
        49.1006,
        -120.8696
      ],
      [
        49.285,
        -119.4019
      ],
      [
        49.7464,
        -115.0607
      ],
      [
        50.0234,
        -111.0339
      ],
      [
        50.2108,
        -108.7952
      ],
      [
        50.3821,
        -107.3611
      ],
      [
        50.57,
        -106.0056
      ]
    ]
  },
  {
    "hex": "a86e85",
    "name": "Global Crossing Airlines",
    "category": "Hired Gun",
    "callsign": "GXA1628",
    "lon": -103.3336,
    "lat": 30.6584,
    "alt": 11582.4,
    "velocity": 212.86,
    "heading": 295.33,
    "trace": [
      [
        26.2301,
        -97.7876
      ],
      [
        27.6628,
        -99.2589
      ],
      [
        29.2651,
        -100.6842
      ],
      [
        29.9889,
        -101.7311
      ],
      [
        30.3349,
        -102.5506
      ],
      [
        30.6584,
        -103.3336
      ]
    ]
  },
  {
    "hex": "a4cb6f",
    "name": "Atlas Air",
    "category": "Hired Gun",
    "callsign": "GTI033",
    "lon": -80.4051,
    "lat": 25.2912,
    "alt": 4533.9,
    "velocity": 217.78,
    "heading": 209.9,
    "trace": [
      [
        25.797,
        -80.2428
      ],
      [
        25.2912,
        -80.4051
      ]
    ]
  }
]